{"version": "1", "message": "ERROR: Hidden Testcases server unreachable.", "problem_id": "cspp1_m10_a1_1", "user_id": "madhavimvh", "score": {"sample": {"0": {"execution_time": 0.06243133544921875, "passed": true}, "1": {"execution_time": 0.0787820816040039, "passed": false}, "2": {"execution_time": 0.062482595443725586, "passed": true}, "3": {"execution_time": 0.06015181541442871, "passed": true}, "4": {"execution_time": 0.06248211860656738, "passed": true}, "5": {"execution_time": 0.062485456466674805, "passed": false}}}, "pylint_score": "-6/10"}